glances_api/__init__.py
glances_api/exceptions.py
glances_api-0.9.0.dist-info/LICENSE
glances_api-0.9.0.dist-info/METADATA
glances_api-0.9.0.dist-info/WHEEL
glances_api-0.9.0.dist-info/RECORD
