Metadata-Version: 2.1
Name: glances_api
Version: 0.9.0
Summary: Python API for interacting with Glances
Home-page: https://github.com/home-assistant-ecosystem/python-glances-api
License: MIT
Author: Fabian Affolter
Author-email: fabian@affolter-engineering.ch
Requires-Python: >=3.11,<4.0
Classifier: Development Status :: 3 - Alpha
Classifier: Environment :: Console
Classifier: Intended Audience :: Developers
Classifier: License :: OSI Approved :: MIT License
Classifier: Operating System :: MacOS :: MacOS X
Classifier: Operating System :: Microsoft :: Windows
Classifier: Operating System :: POSIX
Classifier: Programming Language :: Python :: 3
Classifier: Programming Language :: Python :: 3.11
Classifier: Programming Language :: Python :: 3.12
Classifier: Programming Language :: Python :: 3.13
Classifier: Topic :: Utilities
Requires-Dist: httpx (>=0.23,<1)
Project-URL: Repository, https://github.com/home-assistant-ecosystem/python-glances-api/releases
